toyflow/__init__.py
toyflow/job.py
toyflow/launcher.py
toyflow/resource.py
toyflow/scheduler.py
toyflow/callbacks/__init__.py
toyflow/callbacks/base.py
toyflow/callbacks/logging_callback.py
toyflow/callbacks/rich_callback.py
toyflow/callbacks/web_callback.html
toyflow/callbacks/web_callback.py
toyflow/utils/__init__.py
toyflow/utils/avail_cuda.py
toyflow/utils/json_util.py
toyflow/utils/logger.py
toyflow/utils/python_env.py
toyflow-0.4.3.dist-info/LICENSE
toyflow-0.4.3.dist-info/METADATA
toyflow-0.4.3.dist-info/WHEEL
toyflow-0.4.3.dist-info/top_level.txt
toyflow-0.4.3.dist-info/RECORD
