Metadata-Version: 2.1
Name: toyflow
Version: 0.4.3
Summary: Lightweight flow execution tool.
Home-page: https://github.com/yujiepan-work/toyflow
Author: yujiepan
Author-email: yujiepan@no-email.example.com
License: MIT license
Keywords: toyflow
Requires-Python: >=3.8
License-File: LICENSE
Requires-Dist: pandas
Requires-Dist: flask
